__init__.py
use_aws.py
use_aws_mcp_server-0.2.2.dist-info/licenses/LICENSE
use_aws_mcp_server-0.2.2.dist-info/METADATA
use_aws_mcp_server-0.2.2.dist-info/WHEEL
use_aws_mcp_server-0.2.2.dist-info/entry_points.txt
use_aws_mcp_server-0.2.2.dist-info/top_level.txt
use_aws_mcp_server-0.2.2.dist-info/RECORD
