Metadata-Version: 2.4
Name: use-aws-mcp-server
Version: 0.2.2
Summary: MCP server that provides AWS CLI integration for AI assistants, enabling execution of AWS API calls with proper parameter validation and error handling
Author: moritalous
License: Apache-2.0
Requires-Python: >=3.10
License-File: LICENSE
Requires-Dist: strands-agents-tools>=0.1.1
Dynamic: license-file
